ec2mc/__init__.py
ec2mc/__main__.py
ec2mc/consts.py
ec2mc/aws_setup_src/aws_setup.json
ec2mc/aws_setup_src/iam_policies/admin_perms.json
ec2mc/aws_setup_src/iam_policies/basic_perms.json
ec2mc/aws_setup_src/iam_policies/power_perms.json
ec2mc/aws_setup_src/iam_policies/setup_perms.json
ec2mc/aws_setup_src/ip_handlers/mc_handler.py
ec2mc/aws_setup_src/user_data/cnb_template.yaml
ec2mc/aws_setup_src/user_data/mc_template.yaml
ec2mc/aws_setup_src/user_data/cnb_template/crontabs/ec2mc_crontab
ec2mc/aws_setup_src/user_data/cnb_template/manage_scripts/connection_listener.sh
ec2mc/aws_setup_src/user_data/cnb_template/manage_scripts/shutdown_script.sh
ec2mc/aws_setup_src/user_data/cnb_template/manage_scripts/start_server.sh
ec2mc/aws_setup_src/user_data/cnb_template/manage_scripts/startup_script.sh
ec2mc/aws_setup_src/user_data/cnb_template/mc_folder/server.properties
ec2mc/aws_setup_src/user_data/mc_template/crontabs/ec2mc_crontab
ec2mc/aws_setup_src/user_data/mc_template/manage_scripts/connection_listener.sh
ec2mc/aws_setup_src/user_data/mc_template/manage_scripts/shutdown_script.sh
ec2mc/aws_setup_src/user_data/mc_template/manage_scripts/start_server.sh
ec2mc/aws_setup_src/user_data/mc_template/manage_scripts/startup_script.sh
ec2mc/aws_setup_src/user_data/mc_template/mc_folder/server.properties
ec2mc/aws_setup_src/vpc_security_groups/minecraft_sg.json
ec2mc/commands/__init__.py
ec2mc/commands/address_cmds.py
ec2mc/commands/aws_setup_cmd.py
ec2mc/commands/configure_cmd.py
ec2mc/commands/server_cmds.py
ec2mc/commands/servers_cmds.py
ec2mc/commands/user_cmds.py
ec2mc/commands/address_sub/__init__.py
ec2mc/commands/address_sub/associate_cmd.py
ec2mc/commands/address_sub/disassociate_cmd.py
ec2mc/commands/address_sub/list_cmd.py
ec2mc/commands/address_sub/release_cmd.py
ec2mc/commands/address_sub/request_cmd.py
ec2mc/commands/aws_setup_sub/__init__.py
ec2mc/commands/aws_setup_sub/iam_groups.py
ec2mc-0.2.1.dist-info/METADATA
ec2mc-0.2.1.dist-info/RECORD
ec2mc-0.2.1.dist-info/WHEEL
ec2mc-0.2.1.dist-info/entry_points.txt
ec2mc-0.2.1.dist-info/top_level.txt
