Metadata-Version: 2.1
Name: ec2mc
Version: 0.2.1
Summary: AWS EC2 instance manager for Minecraft servers
Home-page: https://github.com/TakingItCasual/ec2mc
Author: TakingItCasual
Author-email: takingitcasual+gh@gmail.com
License: MIT
Download-URL: https://github.com/TakingItCasual/ec2mc/archive/v0.2.1.tar.gz
Keywords: mc minecraft ssh server aws ec2 iam cloud-config
Platform: UNKNOWN
Classifier: Development Status :: 3 - Alpha
Classifier: Environment :: Console
Classifier: Intended Audience :: System Administrators
Classifier: License :: OSI Approved :: MIT License
Classifier: Natural Language :: English
Classifier: Operating System :: MacOS :: MacOS X
Classifier: Operating System :: Microsoft :: Windows
Classifier: Operating System :: POSIX :: Linux
Classifier: Programming Language :: Python
Classifier: Programming Language :: Python :: 3
Classifier: Programming Language :: Python :: 3.6
Requires-Python: ~=3.6
Requires-Dist: boto3 (~=1.9)
Requires-Dist: nbtlib (~=1.2)
Requires-Dist: deepdiff (~=3.3)
Requires-Dist: cryptography (~=2.3)
Requires-Dist: ruamel.yaml (~=0.15.0)
Requires-Dist: jsonschema (~=2.6)
